fieldmarshal/__init__.py
fieldmarshal-0.0.2.dist-info/LICENSE
fieldmarshal-0.0.2.dist-info/METADATA
fieldmarshal-0.0.2.dist-info/WHEEL
fieldmarshal-0.0.2.dist-info/top_level.txt
fieldmarshal-0.0.2.dist-info/RECORD
