Metadata-Version: 2.1
Name: fieldmarshal
Version: 0.0.2
Summary: Marshal/unmarshal attrs-based data classes to and from JSON
Home-page: https://github.com/trendels/fieldmarshal
Author: Stanis Trendelenburg
Author-email: stanis.trendelenburg@gmail.com
License: MIT
Platform: UNKNOWN
Classifier: License :: OSI Approved :: MIT License
Classifier: Programming Language :: Python :: 3
Classifier: Programming Language :: Python :: 3.6
Classifier: Programming Language :: Python :: 3.7
Classifier: Programming Language :: Python :: 3.8
Requires-Dist: attrs (>=17.4.0)
